{
  "date": "2026-06-21",
  "dagur": 21,
  "manudur": "júní",
  "vikudagur": "Sunnudagur",
  "dagurArsins": 172,
  "sunrise": "02:55",
  "sunset": "00:03",
  "stjornumerki": "Krabbi",
  "nafnadagur": "Álfheiður",
  "atburdir": [
    {
      "ar": "1788",
      "texti": "New Hampshire varð 9. ríkið til að fullgilda stjórnarskrá Bandaríkjanna."
    },
    {
      "ar": "1890",
      "texti": "Fyrsta útgáfa af „The Picture of Dorian Gray“ eftir Oscar Wilde kom út."
    },
    {
      "ar": "1948",
      "texti": "Columbia Records kynnti fyrstu langspilunarplötuna (LP)."
    },
    {
      "ar": "1964",
      "texti": "Þrír borgararéttindafrömuðir hurfu í Mississippi, sem leiddi til mikillar leit."
    },
    {
      "ar": "2004",
      "texti": "SpaceShipOne varð fyrsta einkarekna geimfarið til að ná út í geim."
    }
  ],
  "atburdir_island": [
    {
      "ar": "1915",
      "texti": "Konur á Íslandi fengu kosningarétt og kjörgengi til Alþingis."
    },
    {
      "ar": "1930",
      "texti": "Alþingishátíðin var haldin á Þingvöllum til að minnast 1000 ára afmælis Alþingis."
    }
  ],
  "afmaeli": [
    {
      "nafn": "Jean-Paul Sartre",
      "starfsgrein": "rithöfundur og heimspekingur",
      "ar": "1905"
    },
    {
      "nafn": "Prince William",
      "starfsgrein": "prins af Wales",
      "ar": "1982"
    },
    {
      "nafn": "Lana Del Rey",
      "starfsgrein": "söngkona",
      "ar": "1985"
    }
  ],
  "tonlistUSA": "I Want to Hold Your Hand – The Beatles (1964)",
  "tonlistUK": "You'll Never Walk Alone – Gerry and the Pacemakers (1963)",
  "bio": "Jaws (1975)",
  "ord_dagsins": {
    "ord": "rökkur",
    "skyring": "Tíminn rétt eftir sólsetur eða rétt fyrir sólarupprás þegar birtan er lítil."
  },
  "vissir_thu": "Sumarsólstöður eru oftast 21. júní á norðurhveli jarðar, sem er lengsti dagur ársins.",
  "verdlag": "Árið 1980 kostaði lítri af bensíni um 40 kr. á Íslandi.",
  "stjornuspa": "Krabbi, í dag er góður dagur til að hlúa að fjölskylduböndum og heimili. Leyfðu tilfinningum þínum að leiða þig en gættu þess að ofhugsa ekki smáatriði."
}