{
  "date": "2026-06-20",
  "dagur": 20,
  "manudur": "júní",
  "vikudagur": "Laugardagur",
  "dagurArsins": 171,
  "sunrise": "02:55",
  "sunset": "00:02",
  "stjornumerki": "Tvíburar",
  "nafnadagur": "Sólveig",
  "atburdir": [
    {
      "ar": "1789",
      "texti": "Eiðurinn á tennisvellinum var sýndur í Versölum, mikilvægur atburður í frönsku byltingunni."
    },
    {
      "ar": "1837",
      "texti": "Viktoría varð drottning Bretlands."
    },
    {
      "ar": "1840",
      "texti": "Samuel Morse fékk einkaleyfi á símskeyti sínu."
    },
    {
      "ar": "1944",
      "texti": "Orrustan um Filippseyjahaf lauk í seinni heimsstyrjöldinni."
    },
    {
      "ar": "1991",
      "texti": "Þýska þingið ákvað að flytja höfuðborgina frá Bonn til Berlínar."
    }
  ],
  "atburdir_island": [
    {
      "ar": "1944",
      "texti": "Sveinn Björnsson var kjörinn fyrsti forseti Íslands."
    },
    {
      "ar": "1971",
      "texti": "Fyrsta Reykjavíkurmaraþonið var haldið."
    }
  ],
  "afmaeli": [
    {
      "nafn": "Nicole Kidman",
      "starfsgrein": "leikkona",
      "ar": "1967"
    },
    {
      "nafn": "Lionel Richie",
      "starfsgrein": "tónlistarmaður",
      "ar": "1949"
    },
    {
      "nafn": "John Goodman",
      "starfsgrein": "leikari",
      "ar": "1952"
    }
  ],
  "tonlistUSA": "I Want To Hold Your Hand – The Beatles (1964)",
  "tonlistUK": "I Feel Fine – The Beatles (1964)",
  "bio": "Jaws (1975)",
  "ord_dagsins": {
    "ord": "þrándur",
    "skyring": "Þrándur er gamalt orð yfir naut eða tarf."
  },
  "vissir_thu": "Íslenska hestakynið er eitt það elsta og hreinræktaðasta í heimi, þar sem engum öðrum hestum hefur verið leyft að koma til landsins í yfir 1000 ár.",
  "verdlag": "Árið 1980 kostaði lítri af bensíni um 40 kr. á Íslandi.",
  "stjornuspa": "Tvíburar, í dag gæti óvænt tækifæri birst á sjóndeildarhringnum. Vertu opinn fyrir nýjum hugmyndum og ekki hika við að stökkva á þær."
}